PyDynamic/__init__.py
PyDynamic/signals.py
PyDynamic/deconvolution/__init__.py
PyDynamic/deconvolution/fit_filter.py
PyDynamic/examples/DFT and iDFT with PyDynamic - best practice guide and use cases.ipynb
PyDynamic/examples/__init__.py
PyDynamic/examples/demonstrate_fit_som.py
PyDynamic/examples/working_with_signals.py
PyDynamic/examples/Interpolating/validation_spline_interp_with_MC.py
PyDynamic/examples/Shock calibration/Input estimation for shock acceleration example.ipynb
PyDynamic/examples/Shock calibration/measured_input_accel.txt
PyDynamic/examples/Shock calibration/measured_output_accel.txt
PyDynamic/examples/Shock calibration/sinusoidal_calibration_values.txt
PyDynamic/examples/digital_filtering/Design of a digital deconvolution filter (FIR type).ipynb
PyDynamic/examples/digital_filtering/FIRuncFilter_runtime_comparison.py
PyDynamic/examples/digital_filtering/deconv_FIR.py
PyDynamic/examples/digital_filtering/identify_IIR.py
PyDynamic/examples/digital_filtering/realtime_dwt.py
PyDynamic/examples/digital_filtering/speed_comparison_filter.py
PyDynamic/examples/digital_filtering/uncpropagation_FIR.py
PyDynamic/examples/digital_filtering/uncpropagation_IIR.py
PyDynamic/examples/digital_filtering/validate_DWT_monte_carlo.py
PyDynamic/examples/digital_filtering/validate_FIR_IIR_MC.py
PyDynamic/examples/digital_filtering/validate_FIRuncFilter.py
PyDynamic/examples/uncertainty_for_dft/DFT_amplitude_phase.py
PyDynamic/examples/uncertainty_for_dft/DFTdeconv calibration.dat
PyDynamic/examples/uncertainty_for_dft/DFTdeconv measured_signal.dat
PyDynamic/examples/uncertainty_for_dft/DFTdeconv reference_signal.dat
PyDynamic/examples/uncertainty_for_dft/__init__.py
PyDynamic/examples/uncertainty_for_dft/deconv_DFT.py
PyDynamic/examples/uncertainty_for_dft/__pycache__/DFT_amplitude_phase.cpython-310.pyc
PyDynamic/examples/uncertainty_for_dft/__pycache__/DFT_amplitude_phase.cpython-38.pyc
PyDynamic/examples/uncertainty_for_dft/__pycache__/DFT_amplitude_phase.cpython-39.pyc
PyDynamic-2.5.1.dist-info/METADATA
PyDynamic-2.5.1.dist-info/WHEEL
PyDynamic-2.5.1.dist-info/top_level.txt
PyDynamic-2.5.1.dist-info/RECORD
