Metadata-Version: 2.1
Name: PyDynamic
Version: 2.5.1
Summary: A software package for the analysis of dynamic measurements
Home-page: https://ptb-m4d.github.io/PyDynamic/
Download-URL: https://github.com/PTB-M4D/PyDynamic/releases/download/v2.5.1/PyDynamic-2.5.1.tar.gz
Author: Sascha Eichstädt, Maximilian Gruber, Björn Ludwig, Thomas Bruns, Martin Weber
Author-email: sascha.eichstaedt@ptb.de
License: UNKNOWN
Project-URL: Documentation, https://pydynamic.readthedocs.io/en/v2.5.1/
Project-URL: Source, https://github.com/PTB-M4D/PyDynamic/tree/v2.5.1/
Project-URL: Tracker, https://github.com/PTB-M4D/PyDynamic/issues
Keywords: measurement uncertainty,dynamic measurements,metrology,GUM
Platform: UNKNOWN
Classifier: Development Status :: 7 - Inactive
Classifier: Topic :: Utilities
Classifier: Topic :: Scientific/Engineering
Classifier: Topic :: Software Development :: Libraries :: Python Modules
Classifier: Intended Audience :: Education
Classifier: Intended Audience :: Science/Research
Classifier: License :: OSI Approved :: GNU Lesser General Public License v3 or later (LGPLv3+)
Classifier: Programming Language :: Python :: 3
Classifier: Programming Language :: Python :: 3.8
Classifier: Programming Language :: Python :: 3.9
Classifier: Programming Language :: Python :: 3.10
Classifier: Programming Language :: Python :: 3.11
Classifier: Operating System :: OS Independent
Classifier: Typing :: Typed
Requires-Python: >=3.8
Requires-Dist: matplotlib
Requires-Dist: numpy
Requires-Dist: pandas
Requires-Dist: scipy
Requires-Dist: sympy
Requires-Dist: PyWavelets
Requires-Dist: time-series-buffer
Provides-Extra: dev
Requires-Dist: black[jupyter] ; extra == 'dev'
Requires-Dist: hypothesis ; extra == 'dev'
Requires-Dist: ipykernel ; extra == 'dev'
Requires-Dist: ipython ; extra == 'dev'
Requires-Dist: myst-parser ; extra == 'dev'
Requires-Dist: nbsphinx ; extra == 'dev'
Requires-Dist: pytest ; extra == 'dev'
Requires-Dist: pytest-cov ; extra == 'dev'
Requires-Dist: pytest-custom-exit-code ; extra == 'dev'
Requires-Dist: python-semantic-release (<8) ; extra == 'dev'
Requires-Dist: sphinx ; extra == 'dev'
Requires-Dist: sphinx-rtd-theme ; extra == 'dev'
Requires-Dist: tox ; extra == 'dev'
Requires-Dist: tweepy ; extra == 'dev'
Provides-Extra: examples
Requires-Dist: notebook ; extra == 'examples'
